reflex_icons/AntDesign.py
reflex_icons/BootStrap.py
reflex_icons/BoxIcons.py
reflex_icons/CircumIcons.py
reflex_icons/Devicons.py
reflex_icons/Feather.py
reflex_icons/FlatColorIcons.py
reflex_icons/FontAwesome5.py
reflex_icons/FontAwesome6.py
reflex_icons/GameIcons.py
reflex_icons/GithubOcticonsicons.py
reflex_icons/Grommet-Icons.py
reflex_icons/Heroicons.py
reflex_icons/Heroicons2.py
reflex_icons/IcoMoonFree.py
reflex_icons/Icons8LineAwesome.py
reflex_icons/Ionicons4.py
reflex_icons/Ionicons5.py
reflex_icons/Lucide.py
reflex_icons/MaterialDesignIcons.py
reflex_icons/PhosphorIcons.py
reflex_icons/RadixIcons.py
reflex_icons/SimpleIcons.py
reflex_icons/SimpleLineIcons.py
reflex_icons/TablerIcons.py
reflex_icons/ThemifyIcons.py
reflex_icons/Typicons.py
reflex_icons/VSCodeIcons.py
reflex_icons/WeatherIcons.py
reflex_icons/__init__.py
reflex_icons/css_gg.py
reflex_icons/extractor.py
reflex_icons-1.0.2.dist-info/LICENSE
reflex_icons-1.0.2.dist-info/METADATA
reflex_icons-1.0.2.dist-info/WHEEL
reflex_icons-1.0.2.dist-info/top_level.txt
reflex_icons-1.0.2.dist-info/RECORD
