Metadata-Version: 2.1
Name: reflex-icons
Version: 1.0.2
Summary: This library provides all icons of React-icons wrapped for ReFlex framework
Home-page: https://github.com/saurabhwadekar/Reflex-Icons
Author: Saurabh Wadekar [ INDIA ]
Maintainer: Saurabh Wadekar
Maintainer-email: saurabhwadekar420@gmail.com
License: MIT
Keywords: react icons,icons,reflex-icons,reflex
License-File: LICENSE
Requires-Dist: reflex
